mediawiki/__init__.py
mediawiki/configuraton.py
mediawiki/exceptions.py
mediawiki/mediawiki.py
mediawiki/mediawikipage.py
mediawiki/py.typed
mediawiki/utilities.py
pymediawiki-0.7.5.dist-info/LICENSE
pymediawiki-0.7.5.dist-info/METADATA
pymediawiki-0.7.5.dist-info/WHEEL
pymediawiki-0.7.5.dist-info/top_level.txt
pymediawiki-0.7.5.dist-info/RECORD
